pyyql/__init__.py
pyyql/pyyql.py
pyyql/version.py
pyyql/yaml_engine.py
pyyql/yql.py
pyyql/utils/__init__.py
pyyql/utils/expression_parser.py
pyyql-0.1.2.dist-info/licenses/LICENSE
pyyql-0.1.2.dist-info/METADATA
pyyql-0.1.2.dist-info/WHEEL
pyyql-0.1.2.dist-info/top_level.txt
pyyql-0.1.2.dist-info/RECORD
