Metadata-Version: 2.4
Name: pyyql
Version: 0.1.2
Summary: Declarative PySpark SQL Engine using YAML configurations
Home-page: https://github.com/yourusername/pyyql
Author: Your Name
Author-email: Your Name <your.email@example.com>
License: MIT
Project-URL: Homepage, https://github.com/yourusername/pyyql
Project-URL: Repository, https://github.com/yourusername/pyyql
Project-URL: Documentation, https://pyyql.readthedocs.io
Project-URL: Bug Tracker, https://github.com/yourusername/pyyql/issues
Classifier: Development Status :: 3 - Alpha
Classifier: Intended Audience :: Developers
Classifier: License :: OSI Approved :: MIT License
Classifier: Programming Language :: Python :: 3
Classifier: Programming Language :: Python :: 3.7
Classifier: Programming Language :: Python :: 3.8
Classifier: Programming Language :: Python :: 3.9
Classifier: Programming Language :: Python :: 3.10
Classifier: Programming Language :: Python :: 3.11
Requires-Python: >=3.7
License-File: LICENSE
Requires-Dist: pyspark>=3.0.0
Requires-Dist: PyYAML>=5.4.0
Provides-Extra: dev
Requires-Dist: pytest>=6.0; extra == "dev"
Requires-Dist: pytest-cov>=2.0; extra == "dev"
Requires-Dist: black>=21.0; extra == "dev"
Requires-Dist: flake8>=3.9; extra == "dev"
Requires-Dist: mypy>=0.900; extra == "dev"
Requires-Dist: pre-commit>=2.0; extra == "dev"
Provides-Extra: docs
Requires-Dist: mkdocs>=1.2; extra == "docs"
Requires-Dist: mkdocs-material>=7.0; extra == "docs"
Requires-Dist: mkdocstrings>=0.15; extra == "docs"
Dynamic: author
Dynamic: home-page
Dynamic: license-file
Dynamic: requires-python
